nwt_pytorch/__init__.py
nwt_pytorch/nwt_pytorch.py
nwt_pytorch-0.0.4.dist-info/LICENSE
nwt_pytorch-0.0.4.dist-info/METADATA
nwt_pytorch-0.0.4.dist-info/WHEEL
nwt_pytorch-0.0.4.dist-info/top_level.txt
nwt_pytorch-0.0.4.dist-info/RECORD
