Metadata-Version: 2.1
Name: nwt-pytorch
Version: 0.0.4
Summary: NWT - Pytorch
Home-page: https://github.com/lucidrains/NWT-pytorch
Author: Phil Wang
Author-email: lucidrains@gmail.com
License: MIT
Keywords: artificial intelligence,deep learning,pytorch,audio to video synthesis
Platform: UNKNOWN
Classifier: Development Status :: 4 - Beta
Classifier: Intended Audience :: Developers
Classifier: Topic :: Scientific/Engineering :: Artificial Intelligence
Classifier: License :: OSI Approved :: MIT License
Classifier: Programming Language :: Python :: 3.6
License-File: LICENSE
Requires-Dist: einops (>=0.4)
Requires-Dist: torch
